pytest_fixture_cache/__init__.py
pytest_fixture_cache/decorator.py
pytest_fixture_cache/monad.py
pytest_fixture_cache/plugin.py
pytest_fixture_cache/storage.py
pytest_fixture_cache/utils.py
pytest_fixture_cache-0.1.0.dist-info/METADATA
pytest_fixture_cache-0.1.0.dist-info/WHEEL
pytest_fixture_cache-0.1.0.dist-info/entry_points.txt
pytest_fixture_cache-0.1.0.dist-info/licenses/LICENSE
pytest_fixture_cache-0.1.0.dist-info/RECORD
