Metadata-Version: 2.4
Name: pytest-fixture-cache
Version: 0.1.0
Summary: Smart fixture caching for pytest with SQLite storage
Project-URL: Homepage, https://github.com/yourusername/pytest-fixture-cache
Project-URL: Documentation, https://github.com/yourusername/pytest-fixture-cache#readme
Project-URL: Repository, https://github.com/yourusername/pytest-fixture-cache
Project-URL: Issues, https://github.com/yourusername/pytest-fixture-cache/issues
Project-URL: Changelog, https://github.com/yourusername/pytest-fixture-cache/blob/main/CHANGELOG.md
Author-email: tony <tony.jack0904@gmail.com>
Maintainer-email: tony <tony.jack0904@gmail.com>
License: MIT
License-File: LICENSE
Keywords: cache,fixture,performance,pytest,pytest-plugin,sqlite,testing
Classifier: Development Status :: 4 - Beta
Classifier: Framework :: Pytest
Classifier: Intended Audience :: Developers
Classifier: License :: OSI Approved :: MIT License
Classifier: Operating System :: OS Independent
Classifier: Programming Language :: Python :: 3
Classifier: Programming Language :: Python :: 3.8
Classifier: Programming Language :: Python :: 3.9
Classifier: Programming Language :: Python :: 3.10
Classifier: Programming Language :: Python :: 3.11
Classifier: Programming Language :: Python :: 3.12
Classifier: Topic :: Software Development :: Libraries :: Python Modules
Classifier: Topic :: Software Development :: Testing
Requires-Python: >=3.8
Requires-Dist: pytest>=7.0.0
Provides-Extra: dev
Requires-Dist: black>=23.0.0; extra == 'dev'
Requires-Dist: mypy>=1.0.0; extra == 'dev'
Requires-Dist: pytest-cov>=4.0.0; extra == 'dev'
Requires-Dist: pytest>=7.0.0; extra == 'dev'
Requires-Dist: ruff>=0.1.0; extra == 'dev'
Provides-Extra: monad
Requires-Dist: returns>=0.22.0; extra == 'monad'
